{
  "todos": [
    {
      "id": "5fe3f4ca-193c-4170-83c1-cb5a19908601",
      "title": "Buy food for dinner",
      "completed": false
    },
    {
      "id": "f619466c-a016-4281-b584-7db2795d103d",
      "title": "Call Marie at 10.00 PM",
      "completed": false
    },
    {
      "id": "5fe3f4ca-193c-4170-83c1-cb5a19908602",
      "title": "Write a react blog post",
      "completed": false
    },
    {
      "id": "6027",
      "title": "asds",
      "completed": false
    },
    {
      "id": "7116",
      "title": " a sss ddssas",
      "completed": false
    }
  ]
}
